bellavista/__init__.py
bellavista/bellavista.py
bellavista/input_data.py
bellavista/input_data_merlin.py
bellavista/input_data_merscope.py
bellavista/input_data_xenium.py
bellavista/setup.py
bellavista/utils/__init__.py
bellavista/utils/ngff_writer/__init__.py
bellavista/utils/ngff_writer/array_utils.py
bellavista/utils/ngff_writer/constants.py
bellavista/utils/ngff_writer/dask_utils.py
bellavista/utils/ngff_writer/datastructures.py
bellavista/utils/ngff_writer/json_utils.py
bellavista/utils/ngff_writer/typing.py
bellavista/utils/ngff_writer/validation.py
bellavista/utils/ngff_writer/writer.py
bellavista/utils/ngff_writer/writer_utils.py
bellavista/utils/quickstart/quickstart_xenium_sample.json
bellavista/utils/quickstart/quickstart_xenium_sample_lite.json
bellavista-0.0.2.dist-info/LICENSE.txt
bellavista-0.0.2.dist-info/METADATA
bellavista-0.0.2.dist-info/WHEEL
bellavista-0.0.2.dist-info/entry_points.txt
bellavista-0.0.2.dist-info/top_level.txt
bellavista-0.0.2.dist-info/RECORD
