Metadata-Version: 2.1
Name: bellavista
Version: 0.0.2
Summary: Python package for interactive visualization of imaging-based spatial transcriptomics.
Author-email: Annabelle Coles <acoles@salk.edu>
License: MIT License
Project-URL: Documentation, https://bellavista.readthedocs.io
Project-URL: Repository, https://github.com/pkosurilab/BellaVista.git
Project-URL: Issues, https://github.com/pkosurilab/BellaVista/issues
Keywords: spaital transcriptomics,visualization,napari,python
Classifier: Development Status :: 2 - Pre-Alpha
Requires-Python: >=3.9
License-File: LICENSE.txt
Requires-Dist: tqdm
Requires-Dist: numpy
Requires-Dist: pandas
Requires-Dist: h5py
Requires-Dist: matplotlib
Requires-Dist: ome-zarr
Requires-Dist: napari-ome-zarr
Requires-Dist: zarr
Requires-Dist: imagecodecs
Requires-Dist: shapely
Requires-Dist: pyarrow
Requires-Dist: dask >=2022.02.0
Requires-Dist: napari[all]
Requires-Dist: scikit-image
Requires-Dist: dask-image
